pms_tensorrt/__init__.py
pms_tensorrt/_const.py
pms_tensorrt/_engine_builder.py
pms_tensorrt/_i_type.py
pms_tensorrt/_logger.py
pms_tensorrt/_session.py
pms_tensorrt/_shape_profile.py
pms_tensorrt/_tensor_binding.py
pms_tensorrt/_tensor_mode.py
pms_tensorrt/_trt_builder_flag.py
pms_tensorrt/_trt_proxy.py
pms_tensorrt/_utils.py
pms_tensorrt/_utils_old.py
pms_tensorrt-2.1.3.dist-info/METADATA
pms_tensorrt-2.1.3.dist-info/WHEEL
pms_tensorrt-2.1.3.dist-info/RECORD
