Metadata-Version: 2.4
Name: pms-tensorrt
Version: 2.1.3
Summary: Package for TensorRT
Author: HyeongSeok Kim
Author-email: tiryul@gmail.com
Requires-Python: ==3.12.*
Classifier: Programming Language :: Python :: 3
Classifier: Programming Language :: Python :: 3.12
Requires-Dist: loguru
Requires-Dist: numpy (<2)
